AUTHORS.rst
CONTRIBUTING.rst
HISTORY.rst
LICENSE
MANIFEST.in
README.rst
setup.cfg
setup.py
docs/Makefile
docs/authors.rst
docs/conf.py
docs/contributing.rst
docs/history.rst
docs/index.rst
docs/installation.rst
docs/make.bat
docs/readme.rst
docs/usage.rst
genome_mds/.DS_Store
genome_mds/__init__.py
genome_mds/cli.py
genome_mds/core.py
genome_mds.egg-info/PKG-INFO
genome_mds.egg-info/SOURCES.txt
genome_mds.egg-info/dependency_links.txt
genome_mds.egg-info/entry_points.txt
genome_mds.egg-info/not-zip-safe
genome_mds.egg-info/requires.txt
genome_mds.egg-info/top_level.txt
genome_mds/__pycache__/__init__.cpython-38.pyc
genome_mds/img/logo.png
tests/__init__.py
tests/test_genome_mds.py