Metadata-Version: 1.2
Name: genome-mds
Version: 0.0.1
Summary: Genome-MDS: A graphical two-dimensional comparison tool for prokaryotic genomes
Home-page: https://github.com/omics-tools/genome-mds
Author: Koji Ishiya
Author-email: koji.ishiya@aist.go.jp
License: MIT license
Keywords: genome_mds
Platform: UNKNOWN
Classifier: Development Status :: 2 - Pre-Alpha
Classifier: Intended Audience :: Developers
Classifier: License :: OSI Approved :: MIT License
Classifier: Natural Language :: English
Classifier: Programming Language :: Python :: 3
Classifier: Programming Language :: Python :: 3.6
Classifier: Programming Language :: Python :: 3.7
Classifier: Programming Language :: Python :: 3.8
Classifier: Topic :: Scientific/Engineering :: Bio-Informatics
Requires-Python: >=3.6
